[
  {
    "ContainingType": "QuickFeedback.Controllers.FeedbackController",
    "Method": "GetFeedbackEntries",
    "RelativePath": "api/Feedback",
    "HttpMethod": "GET",
    "IsController": true,
    "Order": 0,
    "Parameters": [],
    "ReturnTypes": [
      {
        "Type": "System.Collections.Generic.IEnumerable\u00601[[QuickFeedback.Models.FeedbackEntry, QuickFeedback, Version=1.0.0.0, Culture=neutral, PublicKeyToken=null]]",
        "MediaTypes": [
          "text/plain",
          "application/json",
          "text/json"
        ],
        "StatusCode": 200
      }
    ]
  },
  {
    "ContainingType": "QuickFeedback.Controllers.FeedbackController",
    "Method": "PostFeedbackEntry",
    "RelativePath": "api/Feedback",
    "HttpMethod": "POST",
    "IsController": true,
    "Order": 0,
    "Parameters": [
      {
        "Name": "feedbackEntry",
        "Type": "QuickFeedback.Models.FeedbackEntry",
        "IsRequired": true
      }
    ],
    "ReturnTypes": [
      {
        "Type": "QuickFeedback.Models.FeedbackEntry",
        "MediaTypes": [
          "text/plain",
          "application/json",
          "text/json"
        ],
        "StatusCode": 200
      }
    ]
  }
]